perian/__init__.py
perian/api/__init__.py
perian/api/accelerator_type_api.py
perian/api/billing_api.py
perian/api/instance_type_api.py
perian/api/job_api.py
perian/api/organization_api.py
perian/api_client.py
perian/api_response.py
perian/configuration.py
perian/exceptions.py
perian/models/__init__.py
perian/models/accelerator_data_view.py
perian/models/accelerator_name.py
perian/models/accelerator_query_input.py
perian/models/accelerator_query_output.py
perian/models/accelerator_type_not_found_error.py
perian/models/accelerator_type_query.py
perian/models/accelerator_type_view.py
perian/models/accelerator_vendor.py
perian/models/amount.py
perian/models/attributes_hash.py
perian/models/availability.py
perian/models/availability_query_input.py
perian/models/availability_query_output.py
perian/models/availability_source.py
perian/models/bandwidth.py
perian/models/bandwidth_limits.py
perian/models/bandwidth_sla.py
perian/models/bandwidth_units.py
perian/models/bill.py
perian/models/bill_item.py
perian/models/billing_granularity.py
perian/models/compute_instance_type.py
perian/models/container_file.py
perian/models/cpu.py
perian/models/cpu_data.py
perian/models/cpu_query_input.py
perian/models/cpu_query_output.py
perian/models/create_job_request.py
perian/models/create_job_success.py
perian/models/credit_top_up_request.py
perian/models/credit_top_up_response.py
perian/models/currency.py
perian/models/default_client_error.py
perian/models/default_server_error.py
perian/models/default_success.py
perian/models/description.py
perian/models/docker_metadata.py
perian/models/docker_registry_credentials.py
perian/models/docker_run_parameters.py
perian/models/get_accelerator_type_request.py
perian/models/get_accelerator_types_success.py
perian/models/get_instance_type_request.py
perian/models/get_instance_types_success.py
perian/models/get_jobs_success.py
perian/models/get_organization_audit_logs_success.py
perian/models/http_validation_error.py
perian/models/id.py
perian-1.0.0.dist-info/METADATA
perian-1.0.0.dist-info/WHEEL
perian-1.0.0.dist-info/RECORD
